README
setup.cfg
setup.py
epubtools/__init__.py
epubtools/settings.py
epubtools.egg-info/PKG-INFO
epubtools.egg-info/SOURCES.txt
epubtools.egg-info/dependency_links.txt
epubtools.egg-info/entry_points.txt
epubtools.egg-info/not-zip-safe
epubtools.egg-info/requires.txt
epubtools.egg-info/top_level.txt
epubtools_base.egg-info/PKG-INFO
epubtools_base.egg-info/SOURCES.txt
epubtools_base.egg-info/dependency_links.txt
epubtools_base.egg-info/entry_points.txt
epubtools_base.egg-info/not-zip-safe
epubtools_base.egg-info/requires.txt
epubtools_base.egg-info/top_level.txt