Metadata-Version: 1.0
Name: epubtools-base
Version: 1.0.0dev-r131
Summary: Library for common epub file handling
Home-page: http://code.google.com/p/epub-tools/
Author: Liza Daly
Author-email: liza@threepress.org
License: New BSD
Keywords: epub
Platform: UNKNOWN
